README.md
setup.cfg
setup.py
mozart/__init__.py
mozart/__main__.py
mozart/__version__.py
mozart/cli.py
mozart/config.py
mozart.egg-info/PKG-INFO
mozart.egg-info/SOURCES.txt
mozart.egg-info/dependency_links.txt
mozart.egg-info/entry_points.txt
mozart.egg-info/requires.txt
mozart.egg-info/top_level.txt
mozart/music/__init__.py
mozart/music/base.py
mozart/music/exception.py
mozart/music/netease.py
mozart/music/qq.py
mozart/music/xiami.py