Metadata-Version: 1.2
Name: mozart
Version: 1.0.3
Summary: Nice API for developers who like music™
Home-page: https://github.com/kushao1267/MusicAPI
Author: krusjra
Author-email: jianliu001922@gmail.com
License: UNKNOWN
Keywords: music,api,mozart
Platform: UNKNOWN
Classifier: Environment :: Console
Classifier: Intended Audience :: Developers
Classifier: Programming Language :: Python
Classifier: Programming Language :: Python :: 3
Classifier: Programming Language :: Python :: 3 :: Only
Classifier: Programming Language :: Python :: 3.5
Classifier: Programming Language :: Python :: 3.6
Classifier: Programming Language :: Python :: 3.7
Classifier: Operating System :: OS Independent
Classifier: License :: OSI Approved :: MIT License
Classifier: Topic :: Internet
Classifier: Topic :: Internet :: WWW/HTTP
Classifier: Topic :: Multimedia
Classifier: Topic :: Multimedia :: Sound/Audio
Classifier: Topic :: Utilities
Requires-Python: >=3.6.0
